tg_bot_sender
