Metadata-Version: 2.1
Name: tg-bot-sender
Version: 0.5
Summary: This lib for sending message to tg bots
Author-email: poznkirill3@gmail.com
